pyEGAF/__init__.py
pyEGAF/analysis.py
pyEGAF/base_egaf.py
pyEGAF/cap_gam.py
pyEGAF/cross_section.py
pyEGAF/decay.py
pyEGAF/file_handler.py
pyEGAF/pyEGAF.py
pyEGAF/separation.py
pyEGAF/EGAF_ENSDF/EGAF_03_100MO_ng_101MO.ens
pyEGAF/EGAF_ENSDF/EGAF_03_100RU_ng_101RU.ens
pyEGAF/EGAF_ENSDF/EGAF_03_101RU_ng_102RU.ens
pyEGAF/EGAF_ENSDF/EGAF_03_102PD_ng_103PD.ens
pyEGAF/EGAF_ENSDF/EGAF_03_102RU_ng_103RU.ens
pyEGAF/EGAF_ENSDF/EGAF_03_103RH_ng_104RH.ens
pyEGAF/EGAF_ENSDF/EGAF_03_104PD_ng_105PD.ens
pyEGAF/EGAF_ENSDF/EGAF_03_104RU_ng_105RU.ens
pyEGAF/EGAF_ENSDF/EGAF_03_105PD_ng_106PD.ens
pyEGAF/EGAF_ENSDF/EGAF_03_106PD_ng_107PD.ens
pyEGAF/EGAF_ENSDF/EGAF_03_107AG_ng_108AG.ens
pyEGAF/EGAF_ENSDF/EGAF_03_108PD_ng_109PD.ens
pyEGAF/EGAF_ENSDF/EGAF_03_109AG_ng_110AG.ens
pyEGAF/EGAF_ENSDF/EGAF_03_10B_ng_11B.ens
pyEGAF/EGAF_ENSDF/EGAF_03_110CD_ng_111CD.ens
pyEGAF/EGAF_ENSDF/EGAF_03_110PD_ng_111PD.ens
pyEGAF/EGAF_ENSDF/EGAF_03_111CD_ng_112CD.ens
pyEGAF/EGAF_ENSDF/EGAF_03_113CD_ng_114CD.ens
pyEGAF/EGAF_ENSDF/EGAF_03_113IN_ng_114IN.ens
pyEGAF/EGAF_ENSDF/EGAF_03_115IN_ng_116IN.ens
pyEGAF/EGAF_ENSDF/EGAF_03_115SN_ng_116SN.ens
pyEGAF/EGAF_ENSDF/EGAF_03_116SN_ng_117SN.ens
pyEGAF/EGAF_ENSDF/EGAF_03_117SN_ng_118SN.ens
pyEGAF/EGAF_ENSDF/EGAF_03_118SN_ng_119SN.ens
pyEGAF/EGAF_ENSDF/EGAF_03_119SN_ng_120SN.ens
pyEGAF/EGAF_ENSDF/EGAF_03_120SN_ng_121SN.ens
pyEGAF/EGAF_ENSDF/EGAF_03_121SB_ng_122SB.ens
pyEGAF/EGAF_ENSDF/EGAF_03_122SN_ng_123SN.ens
pyEGAF/EGAF_ENSDF/EGAF_03_122TE_ng_123TE.ens
pyEGAF/EGAF_ENSDF/EGAF_03_123SB_ng_124SB.ens
pyEGAF/EGAF_ENSDF/EGAF_03_123TE_ng_124TE.ens
pyEGAF/EGAF_ENSDF/EGAF_03_124SN_ng_125SN.ens
pyEGAF/EGAF_ENSDF/EGAF_03_124TE_ng_125TE.ens
pyEGAF/EGAF_ENSDF/EGAF_03_124XE_ng_125XE.ens
pyEGAF/EGAF_ENSDF/EGAF_03_125TE_ng_126TE.ens
pyEGAF/EGAF_ENSDF/EGAF_03_126TE_ng_127TE.ens
pyEGAF/EGAF_ENSDF/EGAF_03_127I_ng_128I.ens
pyEGAF/EGAF_ENSDF/EGAF_03_128TE_ng_129TE.ens
pyEGAF/EGAF_ENSDF/EGAF_03_128XE_ng_129XE.ens
pyEGAF/EGAF_ENSDF/EGAF_03_129XE_ng_130XE.ens
pyEGAF-1.0.14.dist-info/METADATA
pyEGAF-1.0.14.dist-info/WHEEL
pyEGAF-1.0.14.dist-info/top_level.txt
pyEGAF-1.0.14.dist-info/RECORD
