Metadata-Version: 2.1
Name: pyEGAF
Version: 1.0.14
Summary: Allows for interaction, manipulation, and analysis of thermal-neutron capture gamma-ray data from the EGAF library.
Home-page: https://github.com/AaronMHurst/python_egaf
Author: Aaron M. Hurst
Author-email: amhurst@berkeley.edu
Classifier: Development Status :: 5 - Production/Stable
Classifier: Intended Audience :: Science/Research
Classifier: License :: OSI Approved :: BSD License
Classifier: Operating System :: MacOS
Classifier: Operating System :: Unix
Classifier: Programming Language :: Python
Classifier: Programming Language :: Python :: 3
Classifier: Programming Language :: Python :: 3.7
Classifier: Topic :: Scientific/Engineering :: Physics
Requires-Dist: numpy
Requires-Dist: pandas
